dbt_logger/__init__.py
dbt_logger/__main__.py
dbt_logger/cli.py
dbt_logger/logger.py
dbt_logger/utils.py
dbt_logger-0.1.1.dist-info/LICENSE
dbt_logger-0.1.1.dist-info/METADATA
dbt_logger-0.1.1.dist-info/WHEEL
dbt_logger-0.1.1.dist-info/entry_points.txt
dbt_logger-0.1.1.dist-info/RECORD
