Metadata-Version: 2.1
Name: dbt-logger
Version: 0.1.1
Summary: A lightweight logging utility for dbt projects
Home-page: https://github.com/TristanSchwartz/dbt-logger
License: MIT
Keywords: dbt,logging,data,analytics
Author: Tristan Schwartz
Requires-Python: >=3.9.2,<3.13
Classifier: Development Status :: 3 - Alpha
Classifier: Intended Audience :: Developers
Classifier: License :: OSI Approved :: MIT License
Classifier: Programming Language :: Python :: 3
Classifier: Programming Language :: Python :: 3.10
Classifier: Programming Language :: Python :: 3.11
Classifier: Programming Language :: Python :: 3.12
Classifier: Programming Language :: Python :: 3.8
Classifier: Programming Language :: Python :: 3.9
Requires-Dist: cryptography (>=41.0.0,<42.0.0)
Requires-Dist: pyyaml (>=6.0.0,<7.0.0)
Requires-Dist: snowflake-connector-python (>=3.0.0,<4.0.0)
Project-URL: Repository, https://github.com/TristanSchwartz/dbt-logger
